README.rst
setup.py
voiceplay/__init__.py
voiceplay.egg-info/PKG-INFO
voiceplay.egg-info/SOURCES.txt
voiceplay.egg-info/dependency_links.txt
voiceplay.egg-info/entry_points.txt
voiceplay.egg-info/not-zip-safe
voiceplay.egg-info/requires.txt
voiceplay.egg-info/top_level.txt
voiceplay/cli/__init__.py
voiceplay/cli/main.py
voiceplay/cli/argparser/__init__.py
voiceplay/cli/argparser/argparser.py
voiceplay/cli/console/__init__.py
voiceplay/cli/console/console.py
voiceplay/config/__init__.py
voiceplay/config/config.py
voiceplay/config/config.yaml.sample
voiceplay/config/configurator.py
voiceplay/database/__init__.py
voiceplay/database/database.py
voiceplay/database/entities.py
voiceplay/datasources/__init__.py
voiceplay/datasources/lastfm.py
voiceplay/datasources/mbapi.py
voiceplay/datasources/albumart/__init__.py
voiceplay/datasources/albumart/albumart.py
voiceplay/datasources/playlists/__init__.py
voiceplay/datasources/playlists/guesser/__init__.py
voiceplay/datasources/playlists/guesser/guesser.py
voiceplay/datasources/playlists/libraries/__init__.py
voiceplay/datasources/playlists/libraries/asxfile.py
voiceplay/datasources/playlists/libraries/itunes.py
voiceplay/datasources/playlists/libraries/m3ufile.py
voiceplay/datasources/playlists/libraries/plsfile.py
voiceplay/datasources/playlists/libraries/shazam.py
voiceplay/datasources/playlists/libraries/textfile.py
voiceplay/datasources/track/__init__.py
voiceplay/datasources/track/basesource.py
voiceplay/datasources/track/dmn.py
voiceplay/datasources/track/plr.py
voiceplay/datasources/track/vmo.py
voiceplay/datasources/track/ytb.py
voiceplay/extlib/__init__.py
voiceplay/extlib/snowboydetect/__init__.py
voiceplay/extlib/snowboydetect/demo.py
voiceplay/extlib/snowboydetect/demo2.py
voiceplay/extlib/snowboydetect/snowboydecoder.py
voiceplay/extlib/snowboydetect/snowboydetect.py
voiceplay/extlib/snowboydetect/resources/Vicki_en.pmdl
voiceplay/extlib/snowboydetect/resources/Viki_de.pmdl
voiceplay/extlib/snowboydetect/resources/Viki_fr.pmdl
voiceplay/extlib/snowboydetect/resources/common.res
voiceplay/extlib/vlcpython/__init__.py
voiceplay/extlib/vlcpython/vlc.py
voiceplay/logger/__init__.py
voiceplay/logger/logger.py
voiceplay/player/__init__.py
