Metadata-Version: 1.1
Name: voiceplay
Version: 0.2.5.9
Summary: Client-side first music centered voice controlled player
Home-page: https://github.com/tb0hdan/voiceplay
Author: Bohdan Turkynewych
Author-email: tb0hdan@gmail.com
License: public domain
Keywords: voiceplay music playlists vlc player
Platform: UNKNOWN
Classifier: Development Status :: 4 - Beta
Classifier: Environment :: Console
Classifier: License :: Public Domain
Classifier: Natural Language :: English
Classifier: Operating System :: MacOS
Classifier: Operating System :: POSIX :: Linux
Classifier: Programming Language :: Python :: 2
Classifier: Programming Language :: Python :: 2.7
Classifier: Programming Language :: Python :: 3
Classifier: Programming Language :: Python :: 3.3
Classifier: Programming Language :: Python :: 3.4
Classifier: Programming Language :: Python :: 3.5
Classifier: Programming Language :: Python :: 3.6
Classifier: Topic :: Internet
Classifier: Topic :: Multimedia :: Sound/Audio :: Players
Classifier: Topic :: Terminals
